litestar_granian/__init__.py
litestar_granian/__metadata__.py
litestar_granian/cli.py
litestar_granian/plugin.py
litestar_granian/py.typed
litestar_granian-0.14.2.dist-info/METADATA
litestar_granian-0.14.2.dist-info/WHEEL
litestar_granian-0.14.2.dist-info/licenses/LICENSE
litestar_granian-0.14.2.dist-info/RECORD
